all_test.py
delPyc.py
setup.cfg
setup.py
all_test.egg-info/PKG-INFO
all_test.egg-info/SOURCES.txt
all_test.egg-info/dependency_links.txt
all_test.egg-info/entry_points.txt
all_test.egg-info/top_level.txt
basic/HomePage.py
basic/__init__.py
public/HTMLTestRunner.py
public/__init__.py
public/baselog.py