Metadata-Version: 1.0
Name: all-test
Version: 1.0
Summary: This is all_test Package
Home-page: UNKNOWN
Author: Me
Author-email: me@example.com
License: UNKNOWN
Platform: UNKNOWN
